Metadata-Version: 2.0
Name: invenio-groups
Version: 0.1.3
Summary: Invenio module that adds support for user groups.
Home-page: https://github.com/inveniosoftware/invenio-groups
Author: CERN
Author-email: info@invenio-software.org
License: GPLv2
Keywords: invenio groups
Platform: any
Classifier: Environment :: Web Environment
Classifier: Intended Audience :: Developers
Classifier: License :: OSI Approved :: GNU General Public License v2 (GPLv2)
Classifier: Operating System :: OS Independent
Classifier: Programming Language :: Python
Classifier: Topic :: Internet :: WWW/HTTP :: Dynamic Content
Classifier: Topic :: Software Development :: Libraries :: Python Modules
Classifier: Programming Language :: Python :: 2
Classifier: Programming Language :: Python :: 2.7
Classifier: Development Status :: 1 - Planning
Requires-Dist: blinker (>=1.3.0)
Requires-Dist: Flask-Breadcrumbs (>=0.2)
Requires-Dist: Flask-Login (>=0.2.7)
Requires-Dist: Flask-Menu (>=0.2)
Requires-Dist: Flask-Registry (>=0.2)
Requires-Dist: Flask (>=0.10.1)
Requires-Dist: invenio-accounts (>=0.1.2)
Requires-Dist: mock (>=1.0.1)
Requires-Dist: six (>=1.7.2)
Requires-Dist: SQLAlchemy-Utils[encrypted] (>=0.30.1)
Requires-Dist: SQLAlchemy (>=1.0)
Requires-Dist: wtforms-alchemy (>=0.13.1)
Requires-Dist: WTForms (>=2.0.1)
Requires-Dist: invenio-upgrader (>=0.1.0)
Provides-Extra: docs
Requires-Dist: Sphinx (>=1.3); extra == 'docs'
Requires-Dist: sphinx-rtd-theme (>=0.1.7); extra == 'docs'
Provides-Extra: tests
Requires-Dist: Flask-Testing (>=0.4.1); extra == 'tests'
Requires-Dist: coverage (>=3.7.1); extra == 'tests'
Requires-Dist: pytest-cov (>=1.8.1); extra == 'tests'
Requires-Dist: pytest-pep8 (>=1.0.6); extra == 'tests'
Requires-Dist: pytest (>=2.7.0); extra == 'tests'
Requires-Dist: unittest2 (>=1.1.0); extra == 'tests'
